copilotcleaner/__init__.py
copilotcleaner/code_tokens.py
copilotcleaner/dir_walker.py
copilotcleaner/remove_tokens.py
copilotcleaner/run.py
copilotcleaner-0.1.dist-info/METADATA
copilotcleaner-0.1.dist-info/WHEEL
copilotcleaner-0.1.dist-info/entry_points.txt
copilotcleaner-0.1.dist-info/top_level.txt
copilotcleaner-0.1.dist-info/RECORD
